pytest_logbook.py
pytest_logbook-1.1.0.dist-info/DESCRIPTION.rst
pytest_logbook-1.1.0.dist-info/METADATA
pytest_logbook-1.1.0.dist-info/RECORD
pytest_logbook-1.1.0.dist-info/WHEEL
pytest_logbook-1.1.0.dist-info/entry_points.txt
pytest_logbook-1.1.0.dist-info/metadata.json
pytest_logbook-1.1.0.dist-info/top_level.txt
