Metadata-Version: 2.0
Name: pytest-logbook
Version: 1.1.0
Summary: py.test plugin to capture logbook log messages
Home-page: http://bitbucket.org/flub/pytest-logbook
Author: Floris Bruynooghe
Author-email: flub@devork.be
License: MIT
Platform: UNKNOWN
Classifier: Development Status :: 5 - Production/Stable
Classifier: Environment :: Console
Classifier: Environment :: Plugins
Classifier: Intended Audience :: Developers
Classifier: License :: DFSG approved
Classifier: License :: OSI Approved :: MIT License
Classifier: Operating System :: OS Independent
Classifier: Programming Language :: Python :: 3
Classifier: Topic :: Software Development :: Testing
Requires-Dist: Logbook (>=0.11.3)
Requires-Dist: pytest (>=2.8)
